jetsetter/__init__.py
jetsetter/cli.py
jetsetter/interpreter.py
jetsetter-0.1.3.dist-info/METADATA
jetsetter-0.1.3.dist-info/WHEEL
jetsetter-0.1.3.dist-info/entry_points.txt
jetsetter-0.1.3.dist-info/licenses/LICENSE
jetsetter-0.1.3.dist-info/RECORD
