Metadata-Version: 2.1
Name: jetsetter
Version: 0.1.3
Summary: A CLI for working with PyCharm intepreters.
Project-URL: homepage, https://github.com/sam-phinizy/jetsetter
Author-email: Sam Phinizy <83414895+sam-phinizy@users.noreply.github.com>
License-File: LICENSE
Requires-Python: >=3.10
Requires-Dist: questionary>=2.0.1
Requires-Dist: typer>=0.9.0
